wi1_bot/__init__.py
wi1_bot/alembic.ini
wi1_bot/config.py
wi1_bot/db.py
wi1_bot/models.py
wi1_bot/push.py
wi1_bot/py.typed
wi1_bot/webhook.py
wi1_bot/arr/__init__.py
wi1_bot/arr/download.py
wi1_bot/arr/episode.py
wi1_bot/arr/movie.py
wi1_bot/arr/radarr.py
wi1_bot/arr/sonarr.py
wi1_bot/arr/util.py
wi1_bot/discord/__init__.py
wi1_bot/discord/bot.py
wi1_bot/discord/helpers.py
wi1_bot/discord/cogs/__init__.py
wi1_bot/discord/cogs/movie.py
wi1_bot/discord/cogs/series.py
wi1_bot/migrations/env.py
wi1_bot/migrations/script.py.mako
wi1_bot/migrations/versions/f4853c024414_initial_migration.py
wi1_bot/scripts/__init__.py
wi1_bot/scripts/add_tag.py
wi1_bot/scripts/migrate.py
wi1_bot/scripts/rescan.py
wi1_bot/scripts/start.py
wi1_bot/scripts/transcode_item.py
wi1_bot/transcoder/__init__.py
wi1_bot/transcoder/ffprobe.py
wi1_bot/transcoder/transcode_queue.py
wi1_bot/transcoder/transcoder.py
wi1_bot-3.1.6.dist-info/METADATA
wi1_bot-3.1.6.dist-info/WHEEL
wi1_bot-3.1.6.dist-info/entry_points.txt
wi1_bot-3.1.6.dist-info/licenses/LICENSE
wi1_bot-3.1.6.dist-info/RECORD
