Metadata-Version: 2.4
Name: wi1-bot
Version: 3.1.6
Summary: Discord bot for Radarr/Sonarr integration
Project-URL: Homepage, https://github.com/wthueb/wi1-bot
Author-email: William Huebner <wilhueb@gmail.com>
License-Expression: MIT
License-File: LICENSE
Classifier: Programming Language :: Python :: 3
Classifier: Programming Language :: Python :: 3 :: Only
Classifier: Programming Language :: Python :: 3.11
Requires-Python: >=3.11
Requires-Dist: alembic>=1.13.0
Requires-Dist: discord-py>=2.3.2
Requires-Dist: flask>=3.0.2
Requires-Dist: pyarr>=5.2.0
Requires-Dist: pydantic-settings>=2.0.0
Requires-Dist: pydantic>=2.0.0
Requires-Dist: pyyaml>=6.0.1
Requires-Dist: requests>=2.32.4
Requires-Dist: sqlalchemy>=2.0.0
